fastlbp_baseline_imbg/Embedding.py
fastlbp_baseline_imbg/LBP.py
fastlbp_baseline_imbg/Viz.py
fastlbp_baseline_imbg/__init__.py
fastlbp_baseline_imbg/__main__.py
fastlbp_baseline_imbg/common.py
fastlbp_baseline_imbg/entrypoint.py
fastlbp_baseline_imbg/numba_funcs.py
fastlbp_baseline_imbg/useful_functions.py
fastlbp_baseline_imbg-0.0.7.dist-info/LICENSE
fastlbp_baseline_imbg-0.0.7.dist-info/METADATA
fastlbp_baseline_imbg-0.0.7.dist-info/WHEEL
fastlbp_baseline_imbg-0.0.7.dist-info/top_level.txt
fastlbp_baseline_imbg-0.0.7.dist-info/RECORD
